{
  "601": {
    "x": 5539.65,
    "y": -793.395,
    "orbits": [
      0,
      2
    ],
    "background": {
      "image": "PSGroupBackground2"
    },
    "nodes": [
      "45788",
      "2121",
      "12518",
      "28503"
    ]
  },
  "602": {
    "x": 5625.38,
    "y": -159.685,
    "orbits": [
      0
    ],
    "nodes": [
      "52714"
    ]
  },
  "603": {
    "x": 5625.38,
    "y": 173.315,
    "orbits": [
      0
    ],
    "nodes": [
      "60180"
    ]
  },
  "604": {
    "x": 5648.1,
    "y": 763.265,
    "orbits": [
      0
    ],
    "nodes": [
      "11239"
    ]
  },
  "605": {
    "x": 5684.5,
    "y": 6907,
    "orbits": [
      0,
      2
    ],
    "background": {
      "image": "PSGroupBackground2"
    },
    "nodes": [
      "5622",
      "25209",
      "30626",
      "8872",
      "6"
    ]
  },
  "606": {
    "x": 5699.73,
    "y": -8158.76,
    "isProxy": true,
    "orbits": [
      2
    ],
    "background": {
      "image": "PSGroupBackground2"
    },
    "nodes": [
      "24452",
      "59585"
    ]
  },
  "607": {
    "x": 5711.94,
    "y": 2129.71,
    "orbits": [
      2
    ],
    "background": {
      "image": "PSGroupBackground2"
    },
    "nodes": [
      "1201",
      "45491",
      "7085"
    ]
  },
  "608": {
    "x": 5739.58,
    "y": 2611.82,
    "orbits": [],
    "nodes": [
      "41866",
      "60942"
    ]
  },
  "609": {
    "x": 5739.58,
    "y": 3785.17,
    "orbits": [
      0,
      2
    ],
    "background": {
      "image": "PSGroupBackground2"
    },
    "nodes": [
      "36801",
      "19228",
      "3362",
      "4788",
      "529"
    ]
  },
  "610": {
    "x": 5741.38,
    "y": -6061.34,
    "orbits": [
      0,
      2
    ],
    "background": {
      "image": "PSGroupBackground2"
    },
    "nodes": [
      "60210",
      "5018",
      "45810",
      "13168",
      "11984",
      "58032"
    ]
  },
  "611": {
    "x": 5787.26,
    "y": -6677.88,
    "orbits": [
      0
    ],
    "nodes": [
      "11455"
    ]
  },
  "612": {
    "x": 5889.17,
    "y": 5087.11,
    "orbits": [
      0,
      2
    ],
    "background": {
      "image": "PSGroupBackground2"
    },
    "nodes": [
      "12794",
      "30455",
      "28658",
      "14804",
      "41119",
      "47212"
    ]
  },
  "613": {
    "x": 5892.88,
    "y": 6475.33,
    "orbits": [
      0,
      2
    ],
    "background": {
      "image": "PSGroupBackground2"
    },
    "nodes": [
      "56023",
      "11678",
      "44306",
      "8458",
      "52288",
      "31513"
    ]
  },
  "614": {
    "x": 5913.73,
    "y": -2868.8,
    "orbits": [
      4
    ],
    "nodes": [
      "3656",
      "58244"
    ]
  },
  "615": {
    "x": 5913.73,
    "y": -487.945,
    "orbits": [
      0
    ],
    "nodes": [
      "59252"
    ]
  },
  "616": {
    "x": 5913.96,
    "y": 6.815,
    "orbits": [
      0
    ],
    "nodes": [
      "59606"
    ]
  },
  "617": {
    "x": 5913.98,
    "y": -1604.45,
    "orbits": [
      4
    ],
    "nodes": [
      "13885",
      "28012"
    ]
  },
  "618": {
    "x": 5916.07,
    "y": 513.095,
    "orbits": [
      0
    ],
    "nodes": [
      "39718"
    ]
  },
  "619": {
    "x": 5916.07,
    "y": 1553.17,
    "orbits": [
      4
    ],
    "nodes": [
      "27283",
      "5616"
    ]
  },
  "620": {
    "x": 5970.17,
    "y": 5493.58,
    "orbits": [
      0
    ],
    "nodes": [
      "22266"
    ]
  },
  "621": {
    "x": 5999.55,
    "y": -4551.19,
    "orbits": [
      0
    ],
    "nodes": [
      "62791"
    ]
  },
  "622": {
    "x": 5999.85,
    "y": 1638.78,
    "orbits": [
      0
    ],
    "nodes": [
      "31508"
    ]
  },
  "623": {
    "x": 5999.85,
    "y": 2611.82,
    "orbits": [
      0
    ],
    "nodes": [
      "37504"
    ]
  },
  "624": {
    "x": 6051.17,
    "y": 5947.19,
    "orbits": [
      0,
      2
    ],
    "background": {
      "image": "PSGroupBackground2"
    },
    "nodes": [
      "9786",
      "4573",
      "33558",
      "3309",
      "41163"
    ]
  },
  "625": {
    "x": 6071.73,
    "y": -2222.54,
    "orbits": [
      0
    ],
    "nodes": [
      "41989"
    ]
  },
  "626": {
    "x": 6077.01,
    "y": 8476.45,
    "isProxy": true,
    "orbits": [
      1
    ],
    "background": {
      "image": "PSGroupBackground1"
    },
    "nodes": [
      "35313"
    ]
  },
  "627": {
    "x": 6116.13,
    "y": 4586.13,
    "orbits": [
      0,
      2
    ],
    "background": {
      "image": "PSGroupBackground2"
    },
    "nodes": [
      "51420",
      "49481",
      "65053",
      "6384"
    ]
  },
  "628": {
    "x": 6143.15,
    "y": -2868.8,
    "orbits": [
      0
    ],
    "nodes": [
      "24050"
    ]
  },
  "629": {
    "x": 6143.15,
    "y": -1604.45,
    "orbits": [
      0
    ],
    "nodes": [
      "46408"
    ]
  },
  "630": {
    "x": 6161.55,
    "y": -4159.59,
    "orbits": [
      0,
      2
    ],
    "background": {
      "image": "PSGroupBackground2"
    },
    "nodes": [
      "46896",
      "4973",
      "5129",
      "9864",
      "59482",
      "47294"
    ]
  },
  "631": {
    "x": 6166.98,
    "y": -4894.82,
    "orbits": [
      0,
      2
    ],
    "background": {
      "image": "PSGroupBackground2"
    },
    "nodes": [
      "18769",
      "61653",
      "38190",
      "1822",
      "857"
    ]
  },
  "632": {
    "x": 6222.09,
    "y": -3627.79,
    "orbits": [
      0,
      2
    ],
    "background": {
      "image": "PSGroupBackground2"
    },
    "nodes": [
      "37616",
      "27962",
      "31501",
      "59556"
    ]
  },
  "633": {
    "x": 6247.75,
    "y": -8199.76,
    "isProxy": true,
    "orbits": [
      1
    ],
    "background": {
      "image": "PSGroupBackground1"
    },
    "nodes": [
      "27819"
    ]
  },
  "634": {
    "x": 6248.55,
    "y": -5716.25,
    "orbits": [
      0,
      2
    ],
    "background": {
      "image": "PSGroupBackground2"
    },
    "nodes": [
      "44540",
      "39814",
      "27190",
      "25770"
    ]
  },
  "635": {
    "x": 6259.04,
    "y": -1878.44,
    "orbits": [
      0
    ],
    "nodes": [
      "47362"
    ]
  },
  "636": {
    "x": 6264.04,
    "y": -2582.81,
    "orbits": [
      0
    ],
    "nodes": [
      "1767"
    ]
  },
  "637": {
    "x": 6292.06,
    "y": -778.435,
    "orbits": [
      0,
      2
    ],
    "background": {
      "image": "PSGroupBackground2"
    },
    "nodes": [
      "20675",
      "19210",
      "43316",
      "47065"
    ]
  },
  "638": {
    "x": 6292.06,
    "y": -278.035,
    "orbits": [
      0,
      2
    ],
    "background": {
      "image": "PSGroupBackground2"
    },
    "nodes": [
      "54868",
      "39938",
      "45360",
      "57030",
      "9535",
      "27865"
    ]
  },
  "639": {
    "x": 6293.55,
    "y": 245.085,
    "orbits": [
      0,
      2
    ],
    "background": {
      "image": "PSGroupBackground2"
    },
    "nodes": [
      "18707",
      "1427",
      "51235",
      "19725"
    ]
  },
  "640": {
    "x": 6293.55,
    "y": 602.755,
    "orbits": [
      0,
      2
    ],
    "background": {
      "image": "PSGroupBackground2"
    },
    "nodes": [
      "34317",
      "4481",
      "56646",
      "25511"
    ]
  },
  "641": {
    "x": 6401.58,
    "y": 2129.71,
    "orbits": [
      0
    ],
    "nodes": [
      "63843"
    ]
  },
  "642": {
    "x": 6406.54,
    "y": -2222.54,
    "orbits": [
      0
    ],
    "nodes": [
      "7112"
    ]
  },
  "643": {
    "x": 6408.53,
    "y": 5574.58,
    "orbits": [
      0,
      2
    ],
    "background": {
      "image": "PSGroupBackground2"
    },
    "nodes": [
      "16882",
      "43491",
      "14400",
      "41420",
      "9393"
    ]
  },
  "644": {
    "x": 6504.09,
    "y": 3271.25,
    "orbits": [
      0,
      2
    ],
    "background": {
      "image": "PSGroupBackground2"
    },
    "nodes": [
      "33196",
      "13202",
      "17171",
      "44179",
      "43385",
      "58474"
    ]
  },
  "645": {
    "x": 6511.65,
    "y": 989.835,
    "orbits": [
      0,
      2
    ],
    "background": {
      "image": "PSGroupBackground2"
    },
    "nodes": [
      "56814",
      "46694",
      "43457",
      "11850",
      "17608",
      "38568"
    ]
  },
  "646": {
    "x": 6609.3,
    "y": -6224.5,
    "orbits": [
      0,
      2
    ],
    "background": {
      "image": "PSGroupBackground2"
    },
    "nodes": [
      "34763",
      "30110",
      "42907",
      "53013",
      "42361"
    ]
  },
  "647": {
    "x": 6693.21,
    "y": 3983.05,
    "orbits": [
      0,
      2
    ],
    "background": {
      "image": "PSGroupBackground2"
    },
    "nodes": [
      "48660",
      "50150",
      "45436",
      "64878",
      "30969",
      "32477",
      "36281"
    ]
  },
  "648": {
    "x": 6693.21,
    "y": 4667.13,
    "orbits": [
      0
    ],
    "nodes": [
      "32555"
    ]
  },
  "649": {
    "x": 6711.3,
    "y": -5797.25,
    "orbits": [
      0
    ],
    "nodes": [
      "36858"
    ]
  },
  "650": {
    "x": 6711.3,
    "y": -5042.82,
    "orbits": [
      0,
      2
    ],
    "background": {
      "image": "PSGroupBackground2"
    },
    "nodes": [
      "61981",
      "63861",
      "60405",
      "25757",
      "47507",
      "49929"
    ]
  },
  "651": {
    "x": 6805.63,
    "y": -4419.19,
    "orbits": [
      0,
      2
    ],
    "background": {
      "image": "PSGroupBackground2"
    },
    "nodes": [
      "25789",
      "54452",
      "43328",
      "59699",
      "15852",
      "16141"
    ]
  },
  "652": {
    "x": 6834.36,
    "y": 2130.82,
    "orbits": [
      2
    ],
    "background": {
      "image": "PSGroupBackground2"
    },
    "nodes": [
      "14292",
      "38348",
      "16079",
      "21758",
      "60735",
      "48614"
    ]
  },
  "653": {
    "x": 6836.94,
    "y": 1557.78,
    "orbits": [
      0,
      2
    ],
    "background": {
      "image": "PSGroupBackground2"
    },
    "nodes": [
      "37619",
      "64235",
      "24133",
      "27371"
    ]
  },
  "654": {
    "x": 6836.94,
    "y": 2693.91,
    "orbits": [
      0,
      2
    ],
    "background": {
      "image": "PSGroupBackground2"
    },
    "nodes": [
      "19858",
      "36221",
      "9206",
      "44316"
    ]
  },
  "655": {
    "x": 6872.46,
    "y": -6076.38,
    "orbits": [
      0
    ],
    "nodes": [
      "23616"
    ]
  },
  "656": {
    "x": 6872.67,
    "y": -3422.68,
    "orbits": [
      0,
      2
    ],
    "background": {
      "image": "PSGroupBackground2"
    },
    "nodes": [
      "32176",
      "60259",
      "11018",
      "1215"
    ]
  },
  "657": {
    "x": 6872.67,
    "y": -1007.92,
    "orbits": [
      0,
      2
    ],
    "background": {
      "image": "PSGroupBackground2"
    },
    "nodes": [
      "38995",
      "8012",
      "7488",
      "8001"
    ]
  },
  "658": {
    "x": 6873.34,
    "y": 4959.02,
    "orbits": [
      0
    ],
    "nodes": [
      "54922"
    ]
  },
  "659": {
    "x": 6925.46,
    "y": -2949.8,
    "orbits": [
      0,
      2
    ],
    "background": {
      "image": "PSGroupBackground2"
    },
    "nodes": [
      "63228",
      "49308",
      "10495",
      "42804"
    ]
  },
  "660": {
    "x": 6925.46,
    "y": -2222.54,
    "orbits": [
      0,
      3
    ],
    "background": {
      "image": "PSGroupBackground3",
      "isHalfImage": true
    },
    "nodes": [
      "53213",
      "3314",
      "27656",
      "61834",
      "42443",
      "25411",
      "3537"
    ]
  },
  "661": {
    "x": 6925.46,
    "y": -1523.45,
    "orbits": [
      0,
      2
    ],
    "background": {
      "image": "PSGroupBackground2"
    },
    "nodes": [
      "40362",
      "25260",
      "27788",
      "292"
    ]
  },
  "662": {
    "x": 7120.69,
    "y": -4006.48,
    "orbits": [
      0,
      2
    ],
    "background": {
      "image": "PSGroupBackground2"
    },
    "nodes": [
      "6615",
      "5022",
      "37532",
      "44339"
    ]
  },
  "663": {
    "x": 7133,
    "y": -5923.23,
    "orbits": [
      0,
      2
    ],
    "background": {
      "image": "PSGroupBackground2"
    },
    "nodes": [
      "64042",
      "21693",
      "5613",
      "38539",
      "54713"
    ]
  },
  "664": {
    "x": 7145.53,
    "y": 3423.75,
    "orbits": [
      0,
      2
    ],
    "background": {
      "image": "PSGroupBackground2"
    },
    "nodes": [
      "64769",
      "23449",
      "36849",
      "23886",
      "7263",
      "1205"
    ]
  },
  "665": {
    "x": 7180.42,
    "y": 1008.58,
    "orbits": [
      0,
      2
    ],
    "background": {
      "image": "PSGroupBackground2"
    },
    "nodes": [
      "29454",
      "62744",
      "18770",
      "63251",
      "49820"
    ]
  },
  "666": {
    "x": 7191,
    "y": 6.795,
    "orbits": [
      4
    ],
    "nodes": [
      "1461"
    ]
  },
  "667": {
    "x": 7201.69,
    "y": -4559.48,
    "orbits": [
      0
    ],
    "nodes": [
      "53456"
    ]
  },
  "668": {
    "x": 7202.4,
    "y": -5285.82,
    "orbits": [
      0,
      2
    ],
    "background": {
      "image": "PSGroupBackground2"
    },
    "nodes": [
      "2959",
      "30427",
      "56186",
      "11162",
      "54887"
    ]
  },
  "669": {
    "x": 7219.81,
    "y": 4667.13,
    "orbits": [
      0,
      2
    ],
    "background": {
      "image": "PSGroupBackground2"
    },
    "nodes": [
      "53574",
      "26002",
      "7659",
      "25738",
      "62759"
    ]
  },
  "670": {
    "x": 7253.25,
    "y": -243.625,
    "orbits": [
      0,
      2
    ],
    "background": {
      "image": "PSGroupBackground2"
    },
    "nodes": [
      "31585",
      "3676",
      "17790",
      "20736"
    ]
  },
  "671": {
    "x": 7258.01,
    "y": 267.535,
    "orbits": [
      0,
      2
    ],
    "background": {
      "image": "PSGroupBackground2"
    },
    "nodes": [
      "15697",
      "2413",
      "30826",
      "31438",
      "11800",
      "52030"
    ]
  },
  "672": {
    "x": 7267.19,
    "y": 1791.65,
    "orbits": [
      0,
      2
    ],
    "background": {
      "image": "PSGroupBackground2"
    },
    "nodes": [
      "9469",
      "59220",
      "65502",
      "31039"
    ]
  },
  "673": {
    "x": 7267.19,
    "y": 2473.92,
    "orbits": [
      0,
      2
    ],
    "background": {
      "image": "PSGroupBackground2"
    },
    "nodes": [
      "57080",
      "42104",
      "49621",
      "58302"
    ]
  },
  "674": {
    "x": 7286.55,
    "y": -769.775,
    "orbits": [
      0,
      2
    ],
    "background": {
      "image": "PSGroupBackground2"
    },
    "nodes": [
      "5802",
      "3424",
      "1405",
      "31197"
    ]
  },
  "675": {
    "x": 7364.98,
    "y": -3542.49,
    "orbits": [
      0
    ],
    "nodes": [
      "35255"
    ]
  },
  "676": {
    "x": 7407.03,
    "y": 669.295,
    "orbits": [
      0,
      2
    ],
    "background": {
      "image": "PSGroupBackground2"
    },
    "nodes": [
      "13375",
      "65427",
      "45202",
      "20953",
      "49391"
    ]
  },
  "677": {
    "x": 7407.61,
    "y": -2872.02,
    "orbits": [
      0,
      2
    ],
    "background": {
      "image": "PSGroupBackground2"
    },
    "nodes": [
      "17749",
      "18747",
      "52789",
      "10414"
    ]
  },
  "678": {
    "x": 7407.61,
    "y": -1725.33,
    "orbits": [
      0,
      2
    ],
    "background": {
      "image": "PSGroupBackground2"
    },
    "nodes": [
      "35851",
      "60592",
      "47484",
      "26148"
    ]
  },
  "679": {
    "x": 7469.86,
    "y": -4880.42,
    "orbits": [
      0
    ],
    "nodes": [
      "24426"
    ]
  },
  "680": {
    "x": 7684,
    "y": -3341.7,
    "orbits": [
      0
    ],
    "nodes": [
      "18182"
    ]
  },
  "681": {
    "x": 7684,
    "y": -2222.56,
    "orbits": [
      0
    ],
    "nodes": [
      "56295"
    ]
  },
  "682": {
    "x": 7684,
    "y": -1088.96,
    "orbits": [
      0
    ],
    "nodes": [
      "46277"
    ]
  },
  "683": {
    "x": 7684,
    "y": -507.985,
    "orbits": [
      0
    ],
    "nodes": [
      "49900"
    ]
  },
  "684": {
    "x": 7684,
    "y": 939.335,
    "orbits": [
      0
    ],
    "nodes": [
      "36287"
    ]
  },
  "685": {
    "x": 7684,
    "y": 2136.2,
    "orbits": [
      0
    ],
    "nodes": [
      "20807"
    ]
  },
  "686": {
    "x": 7684,
    "y": 3504.79,
    "orbits": [
      0
    ],
    "nodes": [
      "12412"
    ]
  },
  "687": {
    "x": 7684,
    "y": 4234.94,
    "orbits": [
      0,
      2
    ],
    "background": {
      "image": "PSGroupBackground2"
    },
    "nodes": [
      "48508",
      "42632",
      "27444",
      "4750",
      "58288",
      "63618",
      "15290"
    ]
  },
  "688": {
    "x": 7797.69,
    "y": -4559.48,
    "orbits": [
      0,
      2,
      3
    ],
    "background": {
      "image": "PSGroupBackground3",
      "isHalfImage": true
    },
    "nodes": [
      "27872",
      "40409",
      "4546",
      "9055",
      "33777",
      "1655",
      "8027",
      "2260",
      "35334",
      "29549",
      "61689"
    ]
  },
  "689": {
    "x": 7922.19,
    "y": 668.065,
    "orbits": [
      0
    ],
    "nodes": [
      "54307"
    ]
  },
  "690": {
    "x": 7941.78,
    "y": -247.355,
    "orbits": [
      0
    ],
    "nodes": [
      "23407"
    ]
  },
  "691": {
    "x": 8003.21,
    "y": 1686.6,
    "orbits": [
      0,
      2
    ],
    "background": {
      "image": "PSGroupBackground2"
    },
    "nodes": [
      "10840",
      "35086",
      "13935",
      "3571"
    ]
  },
  "692": {
    "x": 8003.21,
    "y": 2581.71,
    "orbits": [
      0,
      2
    ],
    "background": {
      "image": "PSGroupBackground2"
    },
    "nodes": [
      "56519",
      "655",
      "45246",
      "61573",
      "6264",
      "37425"
    ]
  },
  "693": {
    "x": 8038.44,
    "y": 47.815,
    "orbits": [
      1
    ],
    "background": {
      "image": "PSGroupBackground1"
    },
    "nodes": [
      "32763",
      "23334",
      "6797"
    ]
  },
  "694": {
    "x": 8151.34,
    "y": -1088.96,
    "orbits": [
      0,
      2
    ],
    "background": {
      "image": "PSGroupBackground2"
    },
    "nodes": [
      "4269",
      "55880",
      "32681",
      "32657"
    ]
  },
  "695": {
    "x": 8153.54,
    "y": -2692.15,
    "orbits": [
      0,
      3
    ],
    "background": {
      "image": "PSGroupBackground3",
      "isHalfImage": true
    },
    "nodes": [
      "55414",
      "22261",
      "56174",
      "38864",
      "47422",
      "44134",
      "11489",
      "8920",
      "36490",
      "7634"
    ]
  },
  "696": {
    "x": 8153.54,
    "y": -1747.19,
    "orbits": [
      0,
      3
    ],
    "background": {
      "image": "PSGroupBackground3",
      "isHalfImage": true
    },
    "nodes": [
      "36225",
      "30745",
      "49568",
      "17908",
      "25775",
      "5629",
      "35384",
      "15614",
      "54791",
      "19050"
    ]
  },
  "697": {
    "x": 8172.15,
    "y": -588.985,
    "orbits": [
      0,
      2
    ],
    "background": {
      "image": "PSGroupBackground2"
    },
    "nodes": [
      "11811",
      "28903",
      "20127",
      "1648",
      "31359",
      "37785"
    ]
  },
  "698": {
    "x": 8197.29,
    "y": -3636.07,
    "orbits": [
      0,
      2,
      3
    ],
    "background": {
      "image": "PSGroupBackground3",
      "isHalfImage": true
    },
    "nodes": [
      "10429",
      "12824",
      "45827",
      "28753",
      "55380",
      "30319",
      "54574",
      "59605",
      "54974",
      "32432",
      "21297"
    ]
  },
  "699": {
    "x": 8291,
    "y": 3504.79,
    "orbits": [
      0,
      3
    ],
    "background": {
      "image": "PSGroupBackground3",
      "isHalfImage": true
    },
    "nodes": [
      "59151",
      "31291",
      "12720",
      "29856",
      "1698",
      "1568",
      "54354",
      "6108",
      "56509",
      "52213"
    ]
  },
  "700": {
    "x": 8532.18,
    "y": 1593.66,
    "orbits": [
      0
    ],
    "nodes": [
      "57006"
    ]
  }
}