{
    "meta": {
      "schema": "naruto-genkai-list/v1",
      "generated_at": "2025-08-18T17:07:29.110913Z",
      "counts": {
        "B": 2,
        "C": 1,
        "D": 1,
        "E": 1,
        "I": 2,
        "J": 2,
        "K": 3,
        "L": 1,
        "M": 3,
        "R": 4,
        "S": 8,
        "T": 2,
        "W": 1,
        "Y": 1
      },
      "total": 32
    },
    "items": [
      "Boil Release",
      "Byakugan",
      "Crystal Release",
      "Dark Release",
      "Explosion Release",
      "Iburi Clan's Kekkei Genkai",
      "Ice Release",
      "Jōgan",
      "Jūgo's Clan's Kekkei Genkai",
      "Ketsuryūgan",
      "Kokugan",
      "Kurama Clan's Kekkei Genkai",
      "Lava Release",
      "Magnet Release",
      "Mangekyō Sharingan",
      "Mud Release",
      "Ranmaru's Kekkei Genkai",
      "Rinha Clan's Kekkei Genkai",
      "Rinnegan",
      "Ryūzetsu's Kekkei Genkai",
      "Sakon and Ukon's Kekkei Genkai",
      "Scorch Release",
      "Senrigan",
      "Sharingan",
      "Shikotsumyaku",
      "Steel Release",
      "Storm Release",
      "Swift Release",
      "Tenseigan",
      "Typhoon Release",
      "Wood Release",
      "Yanaru's Kekkei Genkai"
    ]
  }